STEM_EDX/__init__.py
STEM_EDX/colorscales.py
STEM_EDX/main.py
STEM_EDX/mainwindow.py
STEM_EDX/stem.py
STEM_EDX/utils.py
EDX_AI-1.1.0.dist-info/LICENSE
EDX_AI-1.1.0.dist-info/METADATA
EDX_AI-1.1.0.dist-info/WHEEL
EDX_AI-1.1.0.dist-info/entry_points.txt
EDX_AI-1.1.0.dist-info/top_level.txt
EDX_AI-1.1.0.dist-info/RECORD
