Metadata-Version: 2.2
Name: EDX-AI
Version: 1.1.0
Summary: A package for STEM-EDX data processing and analysis
Home-page: https://gitlab.com/Anthony-Pecquenard/edx-ai
Author: Anthony Pecquenard
Author-email: Anthony Pecquenard <anthony.pecquenard@ens-lyon.fr>
License: MIT License
Project-URL: Documentation, https://anthony-pecquenard.gitlab.io/edx-ai/
Project-URL: Source Code, https://gitlab.com/Anthony-Pecquenard/edx-ai
Requires-Python: >=3.8
License-File: LICENSE
Requires-Dist: numpy
Requires-Dist: PySide6
